alibaba1688search/__init__.py
alibaba1688search/async_session.py
alibaba1688search/models.py
alibaba1688search/sync_session.py
alibaba1688search/utils.py
alibaba1688search-1.0.0.dist-info/licenses/LICENSE
alibaba1688search-1.0.0.dist-info/METADATA
alibaba1688search-1.0.0.dist-info/WHEEL
alibaba1688search-1.0.0.dist-info/top_level.txt
alibaba1688search-1.0.0.dist-info/RECORD
